odoo/addons/ssi_partner_mixin/README.rst
odoo/addons/ssi_partner_mixin/__init__.py
odoo/addons/ssi_partner_mixin/__manifest__.py
odoo/addons/ssi_partner_mixin/models/__init__.py
odoo/addons/ssi_partner_mixin/models/mixin_partner.py
odoo/addons/ssi_partner_mixin/static/description/icon.png
odoo/addons/ssi_partner_mixin/templates/mixin_partner_templates.xml
odoo14_addon_ssi_partner_mixin-14.0.1.3.0.dist-info/METADATA
odoo14_addon_ssi_partner_mixin-14.0.1.3.0.dist-info/WHEEL
odoo14_addon_ssi_partner_mixin-14.0.1.3.0.dist-info/top_level.txt
odoo14_addon_ssi_partner_mixin-14.0.1.3.0.dist-info/RECORD
